sketchpy3/__init__.py
sketchpy3/canvas.py
sketchpy3/library.py
sketchpy3/files/trace.exe
sketchpy3-0.3.3.dist-info/METADATA
sketchpy3-0.3.3.dist-info/WHEEL
sketchpy3-0.3.3.dist-info/top_level.txt
sketchpy3-0.3.3.dist-info/RECORD
