Metadata-Version: 2.1
Name: sketchpy3
Version: 0.3.3
Summary: sketchpy3
Author: Mr Mystery
Author-email: sriramanand23@gmail.com
Keywords: python,sketch,drawing,animation,code hub,pencil sketch,painting,sketchpy,draw,sketching
Classifier: Development Status :: 1 - Planning
Classifier: Intended Audience :: Developers
Classifier: Programming Language :: Python :: 3
Classifier: Operating System :: Microsoft :: Windows
Requires-Dist: opencv-python
Requires-Dist: turtle ==0.0.1
Requires-Dist: wheel
Requires-Dist: Pillow
Requires-Dist: svg.path
Requires-Dist: svgpathtools
Requires-Dist: tqdm
Requires-Dist: requests
Requires-Dist: geocoder
Requires-Dist: geopy
Requires-Dist: torch
